{
  "levelId": "cand-t4-s404",
  "cols": 9,
  "rows": 13,
  "arrows": [
    {
      "id": "arrow-0",
      "headDir": "down",
      "cells": [
        [
          6,
          6
        ],
        [
          6,
          7
        ],
        [
          7,
          7
        ],
        [
          8,
          7
        ],
        [
          9,
          7
        ]
      ]
    },
    {
      "id": "arrow-1",
      "headDir": "left",
      "cells": [
        [
          11,
          2
        ],
        [
          11,
          1
        ],
        [
          12,
          1
        ],
        [
          12,
          0
        ],
        [
          11,
          0
        ]
      ]
    },
    {
      "id": "arrow-2",
      "headDir": "down",
      "cells": [
        [
          9,
          6
        ],
        [
          9,
          5
        ],
        [
          8,
          5
        ],
        [
          7,
          5
        ],
        [
          7,
          4
        ]
      ]
    },
    {
      "id": "arrow-3",
      "headDir": "right",
      "cells": [
        [
          4,
          2
        ],
        [
          4,
          3
        ]
      ]
    },
    {
      "id": "arrow-4",
      "headDir": "up",
      "cells": [
        [
          9,
          8
        ],
        [
          8,
          8
        ],
        [
          7,
          8
        ],
        [
          6,
          8
        ],
        [
          5,
          8
        ]
      ]
    },
    {
      "id": "arrow-5",
      "headDir": "up",
      "cells": [
        [
          6,
          2
        ],
        [
          6,
          3
        ],
        [
          6,
          4
        ]
      ]
    },
    {
      "id": "arrow-6",
      "headDir": "down",
      "cells": [
        [
          12,
          3
        ],
        [
          12,
          2
        ]
      ]
    },
    {
      "id": "arrow-7",
      "headDir": "down",
      "cells": [
        [
          10,
          6
        ],
        [
          11,
          6
        ],
        [
          11,
          7
        ],
        [
          11,
          8
        ]
      ]
    },
    {
      "id": "arrow-8",
      "headDir": "up",
      "cells": [
        [
          3,
          5
        ],
        [
          3,
          4
        ]
      ]
    },
    {
      "id": "arrow-9",
      "headDir": "down",
      "cells": [
        [
          12,
          7
        ],
        [
          12,
          8
        ]
      ]
    },
    {
      "id": "arrow-10",
      "headDir": "left",
      "cells": [
        [
          10,
          1
        ],
        [
          10,
          2
        ],
        [
          10,
          3
        ],
        [
          9,
          3
        ],
        [
          8,
          3
        ],
        [
          7,
          3
        ]
      ]
    },
    {
      "id": "arrow-11",
      "headDir": "right",
      "cells": [
        [
          0,
          0
        ],
        [
          0,
          1
        ],
        [
          0,
          2
        ],
        [
          0,
          3
        ],
        [
          0,
          4
        ]
      ]
    },
    {
      "id": "arrow-12",
      "headDir": "left",
      "cells": [
        [
          7,
          1
        ],
        [
          8,
          1
        ],
        [
          8,
          2
        ],
        [
          9,
          2
        ]
      ]
    }
  ]
}
